clustroai_sdk/__init__.py
clustroai_sdk/async_clustro_adk.py
clustroai_sdk/clustro_sdk.py
clustroai_sdk/logger.py
clustroai_sdk-0.1.2.dist-info/METADATA
clustroai_sdk-0.1.2.dist-info/WHEEL
clustroai_sdk-0.1.2.dist-info/top_level.txt
clustroai_sdk-0.1.2.dist-info/RECORD
